README.md
setup.py
charmstore/__init__.py
charmstore/error.py
charmstore/lib.py
libcharmstore.egg-info/PKG-INFO
libcharmstore.egg-info/SOURCES.txt
libcharmstore.egg-info/dependency_links.txt
libcharmstore.egg-info/requires.txt
libcharmstore.egg-info/top_level.txt