Metadata-Version: 1.2
Name: libcharmstore
Version: 0.0.9
Summary: Library to access charmstore data
Home-page: https://github.com/juju-solutions/libcharmstore
Maintainer: Marco Ceppi
Maintainer-email: marco@ceppi.net
License: LGPL
Platform: UNKNOWN
Classifier: Development Status :: 5 - Production/Stable
Classifier: Intended Audience :: Developers
Classifier: Programming Language :: Python
Classifier: License :: OSI Approved :: GNU Library or Lesser General Public License (LGPL)
